azure/mgmt/consumption/__init__.py
azure/mgmt/consumption/_configuration.py
azure/mgmt/consumption/_consumption_management_client.py
azure/mgmt/consumption/_patch.py
azure/mgmt/consumption/_vendor.py
azure/mgmt/consumption/_version.py
azure/mgmt/consumption/aio/__init__.py
azure/mgmt/consumption/aio/_configuration.py
azure/mgmt/consumption/aio/_consumption_management_client.py
azure/mgmt/consumption/aio/_patch.py
azure/mgmt/consumption/aio/operations/__init__.py
azure/mgmt/consumption/aio/operations/_aggregated_cost_operations.py
azure/mgmt/consumption/aio/operations/_balances_operations.py
azure/mgmt/consumption/aio/operations/_budgets_operations.py
azure/mgmt/consumption/aio/operations/_charges_operations.py
azure/mgmt/consumption/aio/operations/_credits_operations.py
azure/mgmt/consumption/aio/operations/_events_operations.py
azure/mgmt/consumption/aio/operations/_lots_operations.py
azure/mgmt/consumption/aio/operations/_marketplaces_operations.py
azure/mgmt/consumption/aio/operations/_operations.py
azure/mgmt/consumption/aio/operations/_price_sheet_operations.py
azure/mgmt/consumption/aio/operations/_reservation_recommendation_details_operations.py
azure/mgmt/consumption/aio/operations/_reservation_recommendations_operations.py
azure/mgmt/consumption/aio/operations/_reservation_transactions_operations.py
azure/mgmt/consumption/aio/operations/_reservations_details_operations.py
azure/mgmt/consumption/aio/operations/_reservations_summaries_operations.py
azure/mgmt/consumption/aio/operations/_tags_operations.py
azure/mgmt/consumption/aio/operations/_usage_details_operations.py
azure/mgmt/consumption/models/__init__.py
azure/mgmt/consumption/models/_consumption_management_client_enums.py
azure/mgmt/consumption/models/_models_py3.py
azure/mgmt/consumption/operations/__init__.py
azure/mgmt/consumption/operations/_aggregated_cost_operations.py
azure/mgmt/consumption/operations/_balances_operations.py
azure/mgmt/consumption/operations/_budgets_operations.py
azure_mgmt_consumption-9.0.0.dist-info/LICENSE
azure_mgmt_consumption-9.0.0.dist-info/METADATA
azure_mgmt_consumption-9.0.0.dist-info/WHEEL
azure_mgmt_consumption-9.0.0.dist-info/top_level.txt
azure_mgmt_consumption-9.0.0.dist-info/RECORD
